quatlib/__init__.py
quatlib-0.1.0.dist-info/LICENSE.txt
quatlib-0.1.0.dist-info/METADATA
quatlib-0.1.0.dist-info/WHEEL
quatlib-0.1.0.dist-info/top_level.txt
quatlib-0.1.0.dist-info/RECORD
