Metadata-Version: 2.1
Name: quatlib
Version: 0.1.0
Summary: A very basic quaternion library for transformation between quaternion, Rotation matrix, Euler angle and many more.
Home-page: 
Author: Subhadeep Paul
Author-email: sp323511@gmail.com
License: MIT
Keywords: quaternion
Classifier: Development Status :: 5 - Production/Stable
Classifier: Intended Audience :: Education
Classifier: Operating System :: Microsoft :: Windows :: Windows 10
Classifier: License :: OSI Approved :: MIT License
Classifier: Programming Language :: Python :: 3
License-File: LICENSE.txt
Requires-Dist: numpy
Requires-Dist: scipy
